[
  {
    "text": " Apex Class (43)",
    "icon": "fa-solid fa-folder icon-blue",
    "a_attr": {
      "href": null
    },
    "children": [
      {
        "text": "DOZISF__AggregateResultIterable",
        "icon": "fa-solid fa-circle-check icon-success",
        "a_attr": {
          "href": null
        }
      },
      {
        "text": "DOZISF__AggregateResultIterator",
        "icon": "fa-solid fa-circle-check icon-success",
        "a_attr": {
          "href": null
        }
      },
      {
        "text": "DOZISF__BulkExportApi",
        "icon": "fa-solid fa-circle-check icon-success",
        "a_attr": {
          "href": null
        }
      },
      {
        "text": "DOZISF__BulkExportEntities",
        "icon": "fa-solid fa-circle-check icon-success",
        "a_attr": {
          "href": null
        }
      },
      {
        "text": "DOZISF__BulkExportHandler",
        "icon": "fa-solid fa-circle-check icon-success",
        "a_attr": {
          "href": null
        }
      },
      {
        "text": "DOZISF__BulkExportHandlerTest",
        "icon": "fa-solid fa-circle-check icon-success",
        "a_attr": {
          "href": null
        }
      },
      {
        "text": "DOZISF__CallableCompleteJob",
        "icon": "fa-solid fa-circle-check icon-success",
        "a_attr": {
          "href": null
        }
      },
      {
        "text": "DOZISF__CallableCompleteJobTest",
        "icon": "fa-solid fa-circle-check icon-success",
        "a_attr": {
          "href": null
        }
      },
      {
        "text": "DOZISF__CompleteJob",
        "icon": "fa-solid fa-circle-check icon-success",
        "a_attr": {
          "href": null
        }
      },
      {
        "text": "DOZISF__CompleteJobTest",
        "icon": "fa-solid fa-circle-check icon-success",
        "a_attr": {
          "href": null
        }
      },
      {
        "text": "DOZISF__DAL",
        "icon": "fa-solid fa-circle-check icon-success",
        "a_attr": {
          "href": null
        }
      },
      {
        "text": "DOZISF__DeleteIntelligenceWithoutOwnerBatch",
        "icon": "fa-solid fa-circle-check icon-success",
        "a_attr": {
          "href": null
        }
      },
      {
        "text": "DOZISF__DeleteIntelligenceWithoutOwnerBatchTest",
        "icon": "fa-solid fa-circle-check icon-success",
        "a_attr": {
          "href": null
        }
      },
      {
        "text": "DOZISF__DeleteIntelligenceWithoutOwnerScheduler",
        "icon": "fa-solid fa-circle-check icon-success",
        "a_attr": {
          "href": null
        }
      },
      {
        "text": "DOZISF__Entities",
        "icon": "fa-solid fa-circle-check icon-success",
        "a_attr": {
          "href": null
        }
      },
      {
        "text": "DOZISF__FindEntitiesBatch",
        "icon": "fa-solid fa-circle-check icon-success",
        "a_attr": {
          "href": null
        }
      },
      {
        "text": "DOZISF__FindEntitiesBatchTest",
        "icon": "fa-solid fa-circle-check icon-success",
        "a_attr": {
          "href": null
        }
      },
      {
        "text": "DOZISF__IframeTest",
        "icon": "fa-solid fa-circle-check icon-success",
        "a_attr": {
          "href": null
        }
      },
      {
        "text": "DOZISF__InlineIframController",
        "icon": "fa-solid fa-circle-check icon-success",
        "a_attr": {
          "href": null
        }
      },
      {
        "text": "DOZISF__IntelExportApi",
        "icon": "fa-solid fa-circle-check icon-success",
        "a_attr": {
          "href": null
        }
      },
      {
        "text": "DOZISF__IntelExportEntities",
        "icon": "fa-solid fa-circle-check icon-success",
        "a_attr": {
          "href": null
        }
      },
      {
        "text": "DOZISF__IntelExportHandler",
        "icon": "fa-solid fa-circle-check icon-success",
        "a_attr": {
          "href": null
        }
      },
      {
        "text": "DOZISF__IntelExportUpsertBatch",
        "icon": "fa-solid fa-circle-check icon-success",
        "a_attr": {
          "href": null
        }
      },
      {
        "text": "DOZISF__IntelExportUpsertBatchTest",
        "icon": "fa-solid fa-circle-check icon-success",
        "a_attr": {
          "href": null
        }
      },
      {
        "text": "DOZISF__IntelligenceDeleteExcessBatch",
        "icon": "fa-solid fa-circle-check icon-success",
        "a_attr": {
          "href": null
        }
      },
      {
        "text": "DOZISF__IntelligenceDeleteExcessBatchTest",
        "icon": "fa-solid fa-circle-check icon-success",
        "a_attr": {
          "href": null
        }
      },
      {
        "text": "DOZISF__IntelligenceDeleteExcessScheduler",
        "icon": "fa-solid fa-circle-check icon-success",
        "a_attr": {
          "href": null
        }
      },
      {
        "text": "DOZISF__IntelligenceObjectsHandler",
        "icon": "fa-solid fa-circle-check icon-success",
        "a_attr": {
          "href": null
        }
      },
      {
        "text": "DOZISF__IntelligenceObjectsHandlerTest",
        "icon": "fa-solid fa-circle-check icon-success",
        "a_attr": {
          "href": null
        }
      },
      {
        "text": "DOZISF__JWT",
        "icon": "fa-solid fa-circle-check icon-success",
        "a_attr": {
          "href": null
        }
      },
      {
        "text": "DOZISF__JWT_Test",
        "icon": "fa-solid fa-circle-check icon-success",
        "a_attr": {
          "href": null
        }
      },
      {
        "text": "DOZISF__PostInstallClass",
        "icon": "fa-solid fa-circle-check icon-success",
        "a_attr": {
          "href": null
        }
      },
      {
        "text": "DOZISF__PostInstallClassTest",
        "icon": "fa-solid fa-circle-check icon-success",
        "a_attr": {
          "href": null
        }
      },
      {
        "text": "DOZISF__RestUtility",
        "icon": "fa-solid fa-circle-check icon-success",
        "a_attr": {
          "href": null
        }
      },
      {
        "text": "DOZISF__RestUtilityTest",
        "icon": "fa-solid fa-circle-check icon-success",
        "a_attr": {
          "href": null
        }
      },
      {
        "text": "DOZISF__SaFlowEntitiesBatch",
        "icon": "fa-solid fa-circle-check icon-success",
        "a_attr": {
          "href": null
        }
      },
      {
        "text": "DOZISF__SaFlowEntitiesBatchTest",
        "icon": "fa-solid fa-circle-check icon-success",
        "a_attr": {
          "href": null
        }
      },
      {
        "text": "DOZISF__ScheduledCompleteJob",
        "icon": "fa-solid fa-circle-check icon-success",
        "a_attr": {
          "href": null
        }
      },
      {
        "text": "DOZISF__SecurityUtils",
        "icon": "fa-solid fa-circle-check icon-success",
        "a_attr": {
          "href": null
        }
      },
      {
        "text": "DOZISF__TestUtils",
        "icon": "fa-solid fa-circle-check icon-success",
        "a_attr": {
          "href": null
        }
      },
      {
        "text": "DOZISF__UpsertEntitiesBatch",
        "icon": "fa-solid fa-circle-check icon-success",
        "a_attr": {
          "href": null
        }
      },
      {
        "text": "DOZISF__UpsertEntitiesBatchTest",
        "icon": "fa-solid fa-circle-check icon-success",
        "a_attr": {
          "href": null
        }
      },
      {
        "text": "DOZISF__Utils",
        "icon": "fa-solid fa-circle-check icon-success",
        "a_attr": {
          "href": null
        }
      }
    ]
  },
  {
    "text": " Apex Component (1)",
    "icon": "fa-solid fa-folder icon-blue",
    "a_attr": {
      "href": null
    },
    "children": [
      {
        "text": "DOZISF__InlineIframe",
        "icon": "fa-solid fa-circle-check icon-success",
        "a_attr": {
          "href": null
        }
      }
    ]
  },
  {
    "text": " Apex Page (4)",
    "icon": "fa-solid fa-folder icon-blue",
    "a_attr": {
      "href": null
    },
    "children": [
      {
        "text": "DOZISF__ZoomInfoAccountInline",
        "icon": "fa-solid fa-circle-check icon-success",
        "a_attr": {
          "href": null
        }
      },
      {
        "text": "DOZISF__ZoomInfoContactInline",
        "icon": "fa-solid fa-circle-check icon-success",
        "a_attr": {
          "href": null
        }
      },
      {
        "text": "DOZISF__ZoomInfoLeadInline",
        "icon": "fa-solid fa-circle-check icon-success",
        "a_attr": {
          "href": null
        }
      },
      {
        "text": "DOZISF__ZoomInfoMainFrame",
        "icon": "fa-solid fa-circle-check icon-success",
        "a_attr": {
          "href": null
        }
      }
    ]
  },
  {
    "text": " Apex Trigger (3)",
    "icon": "fa-solid fa-folder icon-blue",
    "a_attr": {
      "href": null
    },
    "children": [
      {
        "text": "DOZISF__AccountTrigger",
        "icon": "fa-solid fa-circle-check icon-success",
        "a_attr": {
          "href": null
        }
      },
      {
        "text": "DOZISF__ContactTrigger",
        "icon": "fa-solid fa-circle-check icon-success",
        "a_attr": {
          "href": null
        }
      },
      {
        "text": "DOZISF__LeadTrigger",
        "icon": "fa-solid fa-circle-check icon-success",
        "a_attr": {
          "href": null
        }
      }
    ]
  },
  {
    "text": " Custom Application (1)",
    "icon": "fa-solid fa-folder icon-blue",
    "a_attr": {
      "href": null
    },
    "children": [
      {
        "text": "DOZISF__ZoomInfo",
        "icon": "fa-solid fa-circle-check icon-success",
        "a_attr": {
          "href": null
        }
      }
    ]
  },
  {
    "text": " Custom Field (155)",
    "icon": "fa-solid fa-folder icon-blue",
    "a_attr": {
      "href": null
    },
    "children": [
      {
        "text": "Account (5)",
        "icon": "fa-solid fa-folder icon-blue",
        "a_attr": {
          "href": null
        },
        "children": [
          {
            "text": "Account.DOZISF__ZoomInfo_Enrich_Status__c",
            "icon": "fa-solid fa-circle-check icon-success",
            "a_attr": {
              "href": null
            }
          },
          {
            "text": "Account.DOZISF__ZoomInfo_First_Updated__c",
            "icon": "fa-solid fa-circle-check icon-success",
            "a_attr": {
              "href": null
            }
          },
          {
            "text": "Account.DOZISF__ZoomInfo_Id__c",
            "icon": "fa-solid fa-circle-check icon-success",
            "a_attr": {
              "href": null
            }
          },
          {
            "text": "Account.DOZISF__ZoomInfo_InboxAI_ID__c",
            "icon": "fa-solid fa-circle-check icon-success",
            "a_attr": {
              "href": null
            }
          },
          {
            "text": "Account.DOZISF__ZoomInfo_Last_Updated__c",
            "icon": "fa-solid fa-circle-check icon-success",
            "a_attr": {
              "href": null
            }
          }
        ]
      },
      {
        "text": "Contact (7)",
        "icon": "fa-solid fa-folder icon-blue",
        "a_attr": {
          "href": null
        },
        "children": [
          {
            "text": "Contact.DOZISF__ZoomInfo_Company_ID__c",
            "icon": "fa-solid fa-circle-check icon-success",
            "a_attr": {
              "href": null
            }
          },
          {
            "text": "Contact.DOZISF__ZoomInfo_Enrich_Status__c",
            "icon": "fa-solid fa-circle-check icon-success",
            "a_attr": {
              "href": null
            }
          },
          {
            "text": "Contact.DOZISF__ZoomInfo_First_Updated__c",
            "icon": "fa-solid fa-circle-check icon-success",
            "a_attr": {
              "href": null
            }
          },
          {
            "text": "Contact.DOZISF__ZoomInfo_Id__c",
            "icon": "fa-solid fa-circle-check icon-success",
            "a_attr": {
              "href": null
            }
          },
          {
            "text": "Contact.DOZISF__ZoomInfo_InboxAI_ID__c",
            "icon": "fa-solid fa-circle-check icon-success",
            "a_attr": {
              "href": null
            }
          },
          {
            "text": "Contact.DOZISF__ZoomInfo_Last_Updated__c",
            "icon": "fa-solid fa-circle-check icon-success",
            "a_attr": {
              "href": null
            }
          },
          {
            "text": "Contact.DOZISF__ZoomInfo_Non_Matched_Reason__c",
            "icon": "fa-solid fa-circle-check icon-success",
            "a_attr": {
              "href": null
            }
          }
        ]
      },
      {
        "text": "DOZISF__Complete_Setting__c (9)",
        "icon": "fa-solid fa-folder icon-blue",
        "a_attr": {
          "href": null
        },
        "children": [
          {
            "text": "DOZISF__Complete_Setting__c.DOZISF__Account_Enabled__c",
            "icon": "fa-solid fa-circle-check icon-success",
            "a_attr": {
              "href": null
            }
          },
          {
            "text": "DOZISF__Complete_Setting__c.DOZISF__Account_Query_1__c",
            "icon": "fa-solid fa-circle-check icon-success",
            "a_attr": {
              "href": null
            }
          },
          {
            "text": "DOZISF__Complete_Setting__c.DOZISF__Account_Query_2__c",
            "icon": "fa-solid fa-circle-check icon-success",
            "a_attr": {
              "href": null
            }
          },
          {
            "text": "DOZISF__Complete_Setting__c.DOZISF__Contact_Enabled__c",
            "icon": "fa-solid fa-circle-check icon-success",
            "a_attr": {
              "href": null
            }
          },
          {
            "text": "DOZISF__Complete_Setting__c.DOZISF__Contact_Query_1__c",
            "icon": "fa-solid fa-circle-check icon-success",
            "a_attr": {
              "href": null
            }
          },
          {
            "text": "DOZISF__Complete_Setting__c.DOZISF__Contact_Query_2__c",
            "icon": "fa-solid fa-circle-check icon-success",
            "a_attr": {
              "href": null
            }
          },
          {
            "text": "DOZISF__Complete_Setting__c.DOZISF__Lead_Enabled__c",
            "icon": "fa-solid fa-circle-check icon-success",
            "a_attr": {
              "href": null
            }
          },
          {
            "text": "DOZISF__Complete_Setting__c.DOZISF__Lead_Query_1__c",
            "icon": "fa-solid fa-circle-check icon-success",
            "a_attr": {
              "href": null
            }
          },
          {
            "text": "DOZISF__Complete_Setting__c.DOZISF__Lead_Query_2__c",
            "icon": "fa-solid fa-circle-check icon-success",
            "a_attr": {
              "href": null
            }
          }
        ]
      },
      {
        "text": "DOZISF__JWT_Setting__mdt (6)",
        "icon": "fa-solid fa-folder icon-blue",
        "a_attr": {
          "href": null
        },
        "children": [
          {
            "text": "DOZISF__JWT_Setting__mdt.DOZISF__Audience__c",
            "icon": "fa-solid fa-circle-check icon-success",
            "a_attr": {
              "href": null
            }
          },
          {
            "text": "DOZISF__JWT_Setting__mdt.DOZISF__Issuer__c",
            "icon": "fa-solid fa-circle-check icon-success",
            "a_attr": {
              "href": null
            }
          },
          {
            "text": "DOZISF__JWT_Setting__mdt.DOZISF__Private_Key__c",
            "icon": "fa-solid fa-circle-check icon-success",
            "a_attr": {
              "href": null
            }
          },
          {
            "text": "DOZISF__JWT_Setting__mdt.DOZISF__Subject__c",
            "icon": "fa-solid fa-circle-check icon-success",
            "a_attr": {
              "href": null
            }
          },
          {
            "text": "DOZISF__JWT_Setting__mdt.DOZISF__User_Name__c",
            "icon": "fa-solid fa-circle-check icon-success",
            "a_attr": {
              "href": null
            }
          },
          {
            "text": "DOZISF__JWT_Setting__mdt.DOZISF__Valid_Time__c",
            "icon": "fa-solid fa-circle-check icon-success",
            "a_attr": {
              "href": null
            }
          }
        ]
      },
      {
        "text": "DOZISF__ZoomInfo__c (99)",
        "icon": "fa-solid fa-folder icon-blue",
        "a_attr": {
          "href": null
        },
        "children": [
          {
            "text": "DOZISF__ZoomInfo__c.DOZISF__Account__c",
            "icon": "fa-solid fa-circle-check icon-success",
            "a_attr": {
              "href": null
            }
          },
          {
            "text": "DOZISF__ZoomInfo__c.DOZISF__Alexa_Rank__c",
            "icon": "fa-solid fa-circle-check icon-success",
            "a_attr": {
              "href": null
            }
          },
          {
            "text": "DOZISF__ZoomInfo__c.DOZISF__All_Industries__c",
            "icon": "fa-solid fa-circle-check icon-success",
            "a_attr": {
              "href": null
            }
          },
          {
            "text": "DOZISF__ZoomInfo__c.DOZISF__All_Investors__c",
            "icon": "fa-solid fa-circle-check icon-success",
            "a_attr": {
              "href": null
            }
          },
          {
            "text": "DOZISF__ZoomInfo__c.DOZISF__All_Sub_Industries__c",
            "icon": "fa-solid fa-circle-check icon-success",
            "a_attr": {
              "href": null
            }
          },
          {
            "text": "DOZISF__ZoomInfo__c.DOZISF__Calculated_Job_Function__c",
            "icon": "fa-solid fa-circle-check icon-success",
            "a_attr": {
              "href": null
            }
          },
          {
            "text": "DOZISF__ZoomInfo__c.DOZISF__Calculated_Management_Level__c",
            "icon": "fa-solid fa-circle-check icon-success",
            "a_attr": {
              "href": null
            }
          },
          {
            "text": "DOZISF__ZoomInfo__c.DOZISF__Certification_Date__c",
            "icon": "fa-solid fa-circle-check icon-success",
            "a_attr": {
              "href": null
            }
          },
          {
            "text": "DOZISF__ZoomInfo__c.DOZISF__Certified_Active_Company__c",
            "icon": "fa-solid fa-circle-check icon-success",
            "a_attr": {
              "href": null
            }
          },
          {
            "text": "DOZISF__ZoomInfo__c.DOZISF__Company_City__c",
            "icon": "fa-solid fa-circle-check icon-success",
            "a_attr": {
              "href": null
            }
          },
          {
            "text": "DOZISF__ZoomInfo__c.DOZISF__Company_Country__c",
            "icon": "fa-solid fa-circle-check icon-success",
            "a_attr": {
              "href": null
            }
          },
          {
            "text": "DOZISF__ZoomInfo__c.DOZISF__Company_Description__c",
            "icon": "fa-solid fa-circle-check icon-success",
            "a_attr": {
              "href": null
            }
          },
          {
            "text": "DOZISF__ZoomInfo__c.DOZISF__Company_Fax__c",
            "icon": "fa-solid fa-circle-check icon-success",
            "a_attr": {
              "href": null
            }
          },
          {
            "text": "DOZISF__ZoomInfo__c.DOZISF__Company_isDefunct__c",
            "icon": "fa-solid fa-circle-check icon-success",
            "a_attr": {
              "href": null
            }
          },
          {
            "text": "DOZISF__ZoomInfo__c.DOZISF__Company_LinkedIn_URL__c",
            "icon": "fa-solid fa-circle-check icon-success",
            "a_attr": {
              "href": null
            }
          },
          {
            "text": "DOZISF__ZoomInfo__c.DOZISF__Company_Name__c",
            "icon": "fa-solid fa-circle-check icon-success",
            "a_attr": {
              "href": null
            }
          },
          {
            "text": "DOZISF__ZoomInfo__c.DOZISF__Company_Phone__c",
            "icon": "fa-solid fa-circle-check icon-success",
            "a_attr": {
              "href": null
            }
          },
          {
            "text": "DOZISF__ZoomInfo__c.DOZISF__Company_State__c",
            "icon": "fa-solid fa-circle-check icon-success",
            "a_attr": {
              "href": null
            }
          },
          {
            "text": "DOZISF__ZoomInfo__c.DOZISF__Company_Street__c",
            "icon": "fa-solid fa-circle-check icon-success",
            "a_attr": {
              "href": null
            }
          },
          {
            "text": "DOZISF__ZoomInfo__c.DOZISF__Company_Type__c",
            "icon": "fa-solid fa-circle-check icon-success",
            "a_attr": {
              "href": null
            }
          },
          {
            "text": "DOZISF__ZoomInfo__c.DOZISF__Company_Zip_Code__c",
            "icon": "fa-solid fa-circle-check icon-success",
            "a_attr": {
              "href": null
            }
          },
          {
            "text": "DOZISF__ZoomInfo__c.DOZISF__Company_ZoomInfo_URL__c",
            "icon": "fa-solid fa-circle-check icon-success",
            "a_attr": {
              "href": null
            }
          },
          {
            "text": "DOZISF__ZoomInfo__c.DOZISF__Contact__c",
            "icon": "fa-solid fa-circle-check icon-success",
            "a_attr": {
              "href": null
            }
          },
          {
            "text": "DOZISF__ZoomInfo__c.DOZISF__Contact_Accuracy_Grade__c",
            "icon": "fa-solid fa-circle-check icon-success",
            "a_attr": {
              "href": null
            }
          },
          {
            "text": "DOZISF__ZoomInfo__c.DOZISF__Contact_Accuracy_Score__c",
            "icon": "fa-solid fa-circle-check icon-success",
            "a_attr": {
              "href": null
            }
          },
          {
            "text": "DOZISF__ZoomInfo__c.DOZISF__Contact_City__c",
            "icon": "fa-solid fa-circle-check icon-success",
            "a_attr": {
              "href": null
            }
          },
          {
            "text": "DOZISF__ZoomInfo__c.DOZISF__Contact_Country__c",
            "icon": "fa-solid fa-circle-check icon-success",
            "a_attr": {
              "href": null
            }
          },
          {
            "text": "DOZISF__ZoomInfo__c.DOZISF__Contact_State__c",
            "icon": "fa-solid fa-circle-check icon-success",
            "a_attr": {
              "href": null
            }
          },
          {
            "text": "DOZISF__ZoomInfo__c.DOZISF__Contact_Street__c",
            "icon": "fa-solid fa-circle-check icon-success",
            "a_attr": {
              "href": null
            }
          },
          {
            "text": "DOZISF__ZoomInfo__c.DOZISF__Contact_Zip_Code__c",
            "icon": "fa-solid fa-circle-check icon-success",
            "a_attr": {
              "href": null
            }
          },
          {
            "text": "DOZISF__ZoomInfo__c.DOZISF__Department__c",
            "icon": "fa-solid fa-circle-check icon-success",
            "a_attr": {
              "href": null
            }
          },
          {
            "text": "DOZISF__ZoomInfo__c.DOZISF__Direct_Phone__c",
            "icon": "fa-solid fa-circle-check icon-success",
            "a_attr": {
              "href": null
            }
          },
          {
            "text": "DOZISF__ZoomInfo__c.DOZISF__Education__c",
            "icon": "fa-solid fa-circle-check icon-success",
            "a_attr": {
              "href": null
            }
          },
          {
            "text": "DOZISF__ZoomInfo__c.DOZISF__Email_Address__c",
            "icon": "fa-solid fa-circle-check icon-success",
            "a_attr": {
              "href": null
            }
          },
          {
            "text": "DOZISF__ZoomInfo__c.DOZISF__Email_Matches_Company_Name__c",
            "icon": "fa-solid fa-circle-check icon-success",
            "a_attr": {
              "href": null
            }
          },
          {
            "text": "DOZISF__ZoomInfo__c.DOZISF__Email_Matches_Person_Name__c",
            "icon": "fa-solid fa-circle-check icon-success",
            "a_attr": {
              "href": null
            }
          },
          {
            "text": "DOZISF__ZoomInfo__c.DOZISF__Employee_Count__c",
            "icon": "fa-solid fa-circle-check icon-success",
            "a_attr": {
              "href": null
            }
          },
          {
            "text": "DOZISF__ZoomInfo__c.DOZISF__Employee_Range__c",
            "icon": "fa-solid fa-circle-check icon-success",
            "a_attr": {
              "href": null
            }
          },
          {
            "text": "DOZISF__ZoomInfo__c.DOZISF__Employment_History__c",
            "icon": "fa-solid fa-circle-check icon-success",
            "a_attr": {
              "href": null
            }
          },
          {
            "text": "DOZISF__ZoomInfo__c.DOZISF__Facebook_Followers__c",
            "icon": "fa-solid fa-circle-check icon-success",
            "a_attr": {
              "href": null
            }
          },
          {
            "text": "DOZISF__ZoomInfo__c.DOZISF__Finance_Department_Budget__c",
            "icon": "fa-solid fa-circle-check icon-success",
            "a_attr": {
              "href": null
            }
          },
          {
            "text": "DOZISF__ZoomInfo__c.DOZISF__First_Name__c",
            "icon": "fa-solid fa-circle-check icon-success",
            "a_attr": {
              "href": null
            }
          },
          {
            "text": "DOZISF__ZoomInfo__c.DOZISF__Founded_Year__c",
            "icon": "fa-solid fa-circle-check icon-success",
            "a_attr": {
              "href": null
            }
          },
          {
            "text": "DOZISF__ZoomInfo__c.DOZISF__Free_Email__c",
            "icon": "fa-solid fa-circle-check icon-success",
            "a_attr": {
              "href": null
            }
          },
          {
            "text": "DOZISF__ZoomInfo__c.DOZISF__Full_Name__c",
            "icon": "fa-solid fa-circle-check icon-success",
            "a_attr": {
              "href": null
            }
          },
          {
            "text": "DOZISF__ZoomInfo__c.DOZISF__Funding_Rounds__c",
            "icon": "fa-solid fa-circle-check icon-success",
            "a_attr": {
              "href": null
            }
          },
          {
            "text": "DOZISF__ZoomInfo__c.DOZISF__Generic_Email__c",
            "icon": "fa-solid fa-circle-check icon-success",
            "a_attr": {
              "href": null
            }
          },
          {
            "text": "DOZISF__ZoomInfo__c.DOZISF__HR_Department_Budget__c",
            "icon": "fa-solid fa-circle-check icon-success",
            "a_attr": {
              "href": null
            }
          },
          {
            "text": "DOZISF__ZoomInfo__c.DOZISF__Industry__c",
            "icon": "fa-solid fa-circle-check icon-success",
            "a_attr": {
              "href": null
            }
          },
          {
            "text": "DOZISF__ZoomInfo__c.DOZISF__IT_Department_Budget__c",
            "icon": "fa-solid fa-circle-check icon-success",
            "a_attr": {
              "href": null
            }
          },
          {
            "text": "DOZISF__ZoomInfo__c.DOZISF__Job_Function__c",
            "icon": "fa-solid fa-circle-check icon-success",
            "a_attr": {
              "href": null
            }
          },
          {
            "text": "DOZISF__ZoomInfo__c.DOZISF__Job_Title__c",
            "icon": "fa-solid fa-circle-check icon-success",
            "a_attr": {
              "href": null
            }
          },
          {
            "text": "DOZISF__ZoomInfo__c.DOZISF__Known_First_Name__c",
            "icon": "fa-solid fa-circle-check icon-success",
            "a_attr": {
              "href": null
            }
          },
          {
            "text": "DOZISF__ZoomInfo__c.DOZISF__Known_Last_Name__c",
            "icon": "fa-solid fa-circle-check icon-success",
            "a_attr": {
              "href": null
            }
          },
          {
            "text": "DOZISF__ZoomInfo__c.DOZISF__Last_Funding_Round_Amount__c",
            "icon": "fa-solid fa-circle-check icon-success",
            "a_attr": {
              "href": null
            }
          },
          {
            "text": "DOZISF__ZoomInfo__c.DOZISF__Last_Funding_Round_Date__c",
            "icon": "fa-solid fa-circle-check icon-success",
            "a_attr": {
              "href": null
            }
          },
          {
            "text": "DOZISF__ZoomInfo__c.DOZISF__Last_Mentioned__c",
            "icon": "fa-solid fa-circle-check icon-success",
            "a_attr": {
              "href": null
            }
          },
          {
            "text": "DOZISF__ZoomInfo__c.DOZISF__Last_Name__c",
            "icon": "fa-solid fa-circle-check icon-success",
            "a_attr": {
              "href": null
            }
          },
          {
            "text": "DOZISF__ZoomInfo__c.DOZISF__Last_Updated_Date__c",
            "icon": "fa-solid fa-circle-check icon-success",
            "a_attr": {
              "href": null
            }
          },
          {
            "text": "DOZISF__ZoomInfo__c.DOZISF__Lead__c",
            "icon": "fa-solid fa-circle-check icon-success",
            "a_attr": {
              "href": null
            }
          },
          {
            "text": "DOZISF__ZoomInfo__c.DOZISF__Malformed_Email__c",
            "icon": "fa-solid fa-circle-check icon-success",
            "a_attr": {
              "href": null
            }
          },
          {
            "text": "DOZISF__ZoomInfo__c.DOZISF__Management_Level__c",
            "icon": "fa-solid fa-circle-check icon-success",
            "a_attr": {
              "href": null
            }
          },
          {
            "text": "DOZISF__ZoomInfo__c.DOZISF__Marketing_Department_Budget__c",
            "icon": "fa-solid fa-circle-check icon-success",
            "a_attr": {
              "href": null
            }
          },
          {
            "text": "DOZISF__ZoomInfo__c.DOZISF__Mobile_Phone_Number__c",
            "icon": "fa-solid fa-circle-check icon-success",
            "a_attr": {
              "href": null
            }
          },
          {
            "text": "DOZISF__ZoomInfo__c.DOZISF__NAICS_Code__c",
            "icon": "fa-solid fa-circle-check icon-success",
            "a_attr": {
              "href": null
            }
          },
          {
            "text": "DOZISF__ZoomInfo__c.DOZISF__No_Match_Reason__c",
            "icon": "fa-solid fa-circle-check icon-success",
            "a_attr": {
              "href": null
            }
          },
          {
            "text": "DOZISF__ZoomInfo__c.DOZISF__Normalized_First_Name__c",
            "icon": "fa-solid fa-circle-check icon-success",
            "a_attr": {
              "href": null
            }
          },
          {
            "text": "DOZISF__ZoomInfo__c.DOZISF__Normalized_Last_Name__c",
            "icon": "fa-solid fa-circle-check icon-success",
            "a_attr": {
              "href": null
            }
          },
          {
            "text": "DOZISF__ZoomInfo__c.DOZISF__Notice_Provided_Date__c",
            "icon": "fa-solid fa-circle-check icon-success",
            "a_attr": {
              "href": null
            }
          },
          {
            "text": "DOZISF__ZoomInfo__c.DOZISF__Number_of_Locations__c",
            "icon": "fa-solid fa-circle-check icon-success",
            "a_attr": {
              "href": null
            }
          },
          {
            "text": "DOZISF__ZoomInfo__c.DOZISF__Parent_Company_Name__c",
            "icon": "fa-solid fa-circle-check icon-success",
            "a_attr": {
              "href": null
            }
          },
          {
            "text": "DOZISF__ZoomInfo__c.DOZISF__Parent_Company_ZoomInfo_ID__c",
            "icon": "fa-solid fa-circle-check icon-success",
            "a_attr": {
              "href": null
            }
          },
          {
            "text": "DOZISF__ZoomInfo__c.DOZISF__Past_1_Year_Employee_Growth_Rate__c",
            "icon": "fa-solid fa-circle-check icon-success",
            "a_attr": {
              "href": null
            }
          },
          {
            "text": "DOZISF__ZoomInfo__c.DOZISF__Past_2_Year_Employee_Growth_Rate__c",
            "icon": "fa-solid fa-circle-check icon-success",
            "a_attr": {
              "href": null
            }
          },
          {
            "text": "DOZISF__ZoomInfo__c.DOZISF__Person_Has_Moved__c",
            "icon": "fa-solid fa-circle-check icon-success",
            "a_attr": {
              "href": null
            }
          },
          {
            "text": "DOZISF__ZoomInfo__c.DOZISF__Person_LinkedIn_URL__c",
            "icon": "fa-solid fa-circle-check icon-success",
            "a_attr": {
              "href": null
            }
          },
          {
            "text": "DOZISF__ZoomInfo__c.DOZISF__Person_Looks_like_EU__c",
            "icon": "fa-solid fa-circle-check icon-success",
            "a_attr": {
              "href": null
            }
          },
          {
            "text": "DOZISF__ZoomInfo__c.DOZISF__Primary_Industry__c",
            "icon": "fa-solid fa-circle-check icon-success",
            "a_attr": {
              "href": null
            }
          },
          {
            "text": "DOZISF__ZoomInfo__c.DOZISF__Primary_Sub_Industry__c",
            "icon": "fa-solid fa-circle-check icon-success",
            "a_attr": {
              "href": null
            }
          },
          {
            "text": "DOZISF__ZoomInfo__c.DOZISF__Products_and_Services__c",
            "icon": "fa-solid fa-circle-check icon-success",
            "a_attr": {
              "href": null
            }
          },
          {
            "text": "DOZISF__ZoomInfo__c.DOZISF__Ranking__c",
            "icon": "fa-solid fa-circle-check icon-success",
            "a_attr": {
              "href": null
            }
          },
          {
            "text": "DOZISF__ZoomInfo__c.DOZISF__Revenue__c",
            "icon": "fa-solid fa-circle-check icon-success",
            "a_attr": {
              "href": null
            }
          },
          {
            "text": "DOZISF__ZoomInfo__c.DOZISF__Revenue_Range__c",
            "icon": "fa-solid fa-circle-check icon-success",
            "a_attr": {
              "href": null
            }
          },
          {
            "text": "DOZISF__ZoomInfo__c.DOZISF__SIC_Code__c",
            "icon": "fa-solid fa-circle-check icon-success",
            "a_attr": {
              "href": null
            }
          },
          {
            "text": "DOZISF__ZoomInfo__c.DOZISF__Supplemental_Email_Address__c",
            "icon": "fa-solid fa-circle-check icon-success",
            "a_attr": {
              "href": null
            }
          },
          {
            "text": "DOZISF__ZoomInfo__c.DOZISF__Ticker__c",
            "icon": "fa-solid fa-circle-check icon-success",
            "a_attr": {
              "href": null
            }
          },
          {
            "text": "DOZISF__ZoomInfo__c.DOZISF__Total_Funding__c",
            "icon": "fa-solid fa-circle-check icon-success",
            "a_attr": {
              "href": null
            }
          },
          {
            "text": "DOZISF__ZoomInfo__c.DOZISF__Twitter_Followers__c",
            "icon": "fa-solid fa-circle-check icon-success",
            "a_attr": {
              "href": null
            }
          },
          {
            "text": "DOZISF__ZoomInfo__c.DOZISF__Ultimate_Parent_Company_Name__c",
            "icon": "fa-solid fa-circle-check icon-success",
            "a_attr": {
              "href": null
            }
          },
          {
            "text": "DOZISF__ZoomInfo__c.DOZISF__Ultimate_Parent_Company_ZoomInfo_ID__c",
            "icon": "fa-solid fa-circle-check icon-success",
            "a_attr": {
              "href": null
            }
          },
          {
            "text": "DOZISF__ZoomInfo__c.DOZISF__Website__c",
            "icon": "fa-solid fa-circle-check icon-success",
            "a_attr": {
              "href": null
            }
          },
          {
            "text": "DOZISF__ZoomInfo__c.DOZISF__Within_EU__c",
            "icon": "fa-solid fa-circle-check icon-success",
            "a_attr": {
              "href": null
            }
          },
          {
            "text": "DOZISF__ZoomInfo__c.DOZISF__ZoomInfo_Company_ID__c",
            "icon": "fa-solid fa-circle-check icon-success",
            "a_attr": {
              "href": null
            }
          },
          {
            "text": "DOZISF__ZoomInfo__c.DOZISF__ZoomInfo_Contact_ID__c",
            "icon": "fa-solid fa-circle-check icon-success",
            "a_attr": {
              "href": null
            }
          },
          {
            "text": "DOZISF__ZoomInfo__c.DOZISF__ZoomInfo_Enrich_Status__c",
            "icon": "fa-solid fa-circle-check icon-success",
            "a_attr": {
              "href": null
            }
          },
          {
            "text": "DOZISF__ZoomInfo__c.DOZISF__ZoomInfo_External_Id__c",
            "icon": "fa-solid fa-circle-check icon-success",
            "a_attr": {
              "href": null
            }
          },
          {
            "text": "DOZISF__ZoomInfo__c.DOZISF__ZoomInfo_First_Updated__c",
            "icon": "fa-solid fa-circle-check icon-success",
            "a_attr": {
              "href": null
            }
          },
          {
            "text": "DOZISF__ZoomInfo__c.DOZISF__ZoomInfo_Last_Updated__c",
            "icon": "fa-solid fa-circle-check icon-success",
            "a_attr": {
              "href": null
            }
          },
          {
            "text": "DOZISF__ZoomInfo__c.DOZISF__ZoomInfo_URL__c",
            "icon": "fa-solid fa-circle-check icon-success",
            "a_attr": {
              "href": null
            }
          }
        ]
      },
      {
        "text": "DOZISF__ZoomInfo_Intent__c (9)",
        "icon": "fa-solid fa-folder icon-blue",
        "a_attr": {
          "href": null
        },
        "children": [
          {
            "text": "DOZISF__ZoomInfo_Intent__c.DOZISF__Account__c",
            "icon": "fa-solid fa-circle-check icon-success",
            "a_attr": {
              "href": null
            }
          },
          {
            "text": "DOZISF__ZoomInfo_Intent__c.DOZISF__Categories__c",
            "icon": "fa-solid fa-circle-check icon-success",
            "a_attr": {
              "href": null
            }
          },
          {
            "text": "DOZISF__ZoomInfo_Intent__c.DOZISF__Change_in_Surge_Score__c",
            "icon": "fa-solid fa-circle-check icon-success",
            "a_attr": {
              "href": null
            }
          },
          {
            "text": "DOZISF__ZoomInfo_Intent__c.DOZISF__Intent_ID__c",
            "icon": "fa-solid fa-circle-check icon-success",
            "a_attr": {
              "href": null
            }
          },
          {
            "text": "DOZISF__ZoomInfo_Intent__c.DOZISF__Signal_Date__c",
            "icon": "fa-solid fa-circle-check icon-success",
            "a_attr": {
              "href": null
            }
          },
          {
            "text": "DOZISF__ZoomInfo_Intent__c.DOZISF__Spikes_in_Date_Range__c",
            "icon": "fa-solid fa-circle-check icon-success",
            "a_attr": {
              "href": null
            }
          },
          {
            "text": "DOZISF__ZoomInfo_Intent__c.DOZISF__Surge_Score__c",
            "icon": "fa-solid fa-circle-check icon-success",
            "a_attr": {
              "href": null
            }
          },
          {
            "text": "DOZISF__ZoomInfo_Intent__c.DOZISF__Topic__c",
            "icon": "fa-solid fa-circle-check icon-success",
            "a_attr": {
              "href": null
            }
          },
          {
            "text": "DOZISF__ZoomInfo_Intent__c.DOZISF__ZoomInfo_External_Id__c",
            "icon": "fa-solid fa-circle-check icon-success",
            "a_attr": {
              "href": null
            }
          }
        ]
      },
      {
        "text": "DOZISF__ZoomInfo_Scoop__c (13)",
        "icon": "fa-solid fa-folder icon-blue",
        "a_attr": {
          "href": null
        },
        "children": [
          {
            "text": "DOZISF__ZoomInfo_Scoop__c.DOZISF__Account__c",
            "icon": "fa-solid fa-circle-check icon-success",
            "a_attr": {
              "href": null
            }
          },
          {
            "text": "DOZISF__ZoomInfo_Scoop__c.DOZISF__Contact__c",
            "icon": "fa-solid fa-circle-check icon-success",
            "a_attr": {
              "href": null
            }
          },
          {
            "text": "DOZISF__ZoomInfo_Scoop__c.DOZISF__Date_Published__c",
            "icon": "fa-solid fa-circle-check icon-success",
            "a_attr": {
              "href": null
            }
          },
          {
            "text": "DOZISF__ZoomInfo_Scoop__c.DOZISF__Description__c",
            "icon": "fa-solid fa-circle-check icon-success",
            "a_attr": {
              "href": null
            }
          },
          {
            "text": "DOZISF__ZoomInfo_Scoop__c.DOZISF__First_Name__c",
            "icon": "fa-solid fa-circle-check icon-success",
            "a_attr": {
              "href": null
            }
          },
          {
            "text": "DOZISF__ZoomInfo_Scoop__c.DOZISF__Job_Title__c",
            "icon": "fa-solid fa-circle-check icon-success",
            "a_attr": {
              "href": null
            }
          },
          {
            "text": "DOZISF__ZoomInfo_Scoop__c.DOZISF__Last_Name__c",
            "icon": "fa-solid fa-circle-check icon-success",
            "a_attr": {
              "href": null
            }
          },
          {
            "text": "DOZISF__ZoomInfo_Scoop__c.DOZISF__Lead__c",
            "icon": "fa-solid fa-circle-check icon-success",
            "a_attr": {
              "href": null
            }
          },
          {
            "text": "DOZISF__ZoomInfo_Scoop__c.DOZISF__Scoop_ID__c",
            "icon": "fa-solid fa-circle-check icon-success",
            "a_attr": {
              "href": null
            }
          },
          {
            "text": "DOZISF__ZoomInfo_Scoop__c.DOZISF__Topics__c",
            "icon": "fa-solid fa-circle-check icon-success",
            "a_attr": {
              "href": null
            }
          },
          {
            "text": "DOZISF__ZoomInfo_Scoop__c.DOZISF__Type__c",
            "icon": "fa-solid fa-circle-check icon-success",
            "a_attr": {
              "href": null
            }
          },
          {
            "text": "DOZISF__ZoomInfo_Scoop__c.DOZISF__ZoomInfo_External_Id__c",
            "icon": "fa-solid fa-circle-check icon-success",
            "a_attr": {
              "href": null
            }
          },
          {
            "text": "DOZISF__ZoomInfo_Scoop__c.DOZISF__ZoomInfo_Id__c",
            "icon": "fa-solid fa-circle-check icon-success",
            "a_attr": {
              "href": null
            }
          }
        ]
      },
      {
        "text": "Lead (7)",
        "icon": "fa-solid fa-folder icon-blue",
        "a_attr": {
          "href": null
        },
        "children": [
          {
            "text": "Lead.DOZISF__ZoomInfo_Company_ID__c",
            "icon": "fa-solid fa-circle-check icon-success",
            "a_attr": {
              "href": null
            }
          },
          {
            "text": "Lead.DOZISF__ZoomInfo_Enrich_Status__c",
            "icon": "fa-solid fa-circle-check icon-success",
            "a_attr": {
              "href": null
            }
          },
          {
            "text": "Lead.DOZISF__ZoomInfo_First_Updated__c",
            "icon": "fa-solid fa-circle-check icon-success",
            "a_attr": {
              "href": null
            }
          },
          {
            "text": "Lead.DOZISF__ZoomInfo_Id__c",
            "icon": "fa-solid fa-circle-check icon-success",
            "a_attr": {
              "href": null
            }
          },
          {
            "text": "Lead.DOZISF__ZoomInfo_InboxAI_ID__c",
            "icon": "fa-solid fa-circle-check icon-success",
            "a_attr": {
              "href": null
            }
          },
          {
            "text": "Lead.DOZISF__ZoomInfo_Last_Updated__c",
            "icon": "fa-solid fa-circle-check icon-success",
            "a_attr": {
              "href": null
            }
          },
          {
            "text": "Lead.DOZISF__ZoomInfo_Non_Matched_Reason__c",
            "icon": "fa-solid fa-circle-check icon-success",
            "a_attr": {
              "href": null
            }
          }
        ]
      }
    ]
  },
  {
    "text": " Custom Label (80)",
    "icon": "fa-solid fa-folder icon-blue",
    "a_attr": {
      "href": null
    },
    "children": [
      {
        "text": "DOZISF__Complete_Job_Path",
        "icon": "fa-solid fa-circle-check icon-success",
        "a_attr": {
          "href": null
        }
      },
      {
        "text": "DOZISF__Complete_Job_Path",
        "icon": "fa-solid fa-circle-check icon-success",
        "a_attr": {
          "href": null
        }
      },
      {
        "text": "DOZISF__Create_Bulk_Export_Run_Path",
        "icon": "fa-solid fa-circle-check icon-success",
        "a_attr": {
          "href": null
        }
      },
      {
        "text": "DOZISF__Create_Bulk_Export_Run_Path",
        "icon": "fa-solid fa-circle-check icon-success",
        "a_attr": {
          "href": null
        }
      },
      {
        "text": "DOZISF__Develop_Base_URL",
        "icon": "fa-solid fa-circle-check icon-success",
        "a_attr": {
          "href": null
        }
      },
      {
        "text": "DOZISF__Develop_Base_URL",
        "icon": "fa-solid fa-circle-check icon-success",
        "a_attr": {
          "href": null
        }
      },
      {
        "text": "DOZISF__Develop_Bulk_Export_Base_URL",
        "icon": "fa-solid fa-circle-check icon-success",
        "a_attr": {
          "href": null
        }
      },
      {
        "text": "DOZISF__Develop_Bulk_Export_Base_URL",
        "icon": "fa-solid fa-circle-check icon-success",
        "a_attr": {
          "href": null
        }
      },
      {
        "text": "DOZISF__Develop_Enrich_Base_URL",
        "icon": "fa-solid fa-circle-check icon-success",
        "a_attr": {
          "href": null
        }
      },
      {
        "text": "DOZISF__Develop_Enrich_Base_URL",
        "icon": "fa-solid fa-circle-check icon-success",
        "a_attr": {
          "href": null
        }
      },
      {
        "text": "DOZISF__Develop_UI_Base_URL",
        "icon": "fa-solid fa-circle-check icon-success",
        "a_attr": {
          "href": null
        }
      },
      {
        "text": "DOZISF__Develop_UI_Base_URL",
        "icon": "fa-solid fa-circle-check icon-success",
        "a_attr": {
          "href": null
        }
      },
      {
        "text": "DOZISF__DOZI_Production_UI_Base_URL",
        "icon": "fa-solid fa-circle-check icon-success",
        "a_attr": {
          "href": null
        }
      },
      {
        "text": "DOZISF__DOZI_Production_UI_Base_URL",
        "icon": "fa-solid fa-circle-check icon-success",
        "a_attr": {
          "href": null
        }
      },
      {
        "text": "DOZISF__Get_Find_Duplicate_Queries_Path",
        "icon": "fa-solid fa-circle-check icon-success",
        "a_attr": {
          "href": null
        }
      },
      {
        "text": "DOZISF__Get_Find_Duplicate_Queries_Path",
        "icon": "fa-solid fa-circle-check icon-success",
        "a_attr": {
          "href": null
        }
      },
      {
        "text": "DOZISF__Get_Find_Relation_Queries_Path",
        "icon": "fa-solid fa-circle-check icon-success",
        "a_attr": {
          "href": null
        }
      },
      {
        "text": "DOZISF__Get_Find_Relation_Queries_Path",
        "icon": "fa-solid fa-circle-check icon-success",
        "a_attr": {
          "href": null
        }
      },
      {
        "text": "DOZISF__Get_Intel_Export_Run_Path",
        "icon": "fa-solid fa-circle-check icon-success",
        "a_attr": {
          "href": null
        }
      },
      {
        "text": "DOZISF__Get_Intel_Export_Run_Path",
        "icon": "fa-solid fa-circle-check icon-success",
        "a_attr": {
          "href": null
        }
      },
      {
        "text": "DOZISF__Get_Intel_Records_For_Upsert_Path",
        "icon": "fa-solid fa-circle-check icon-success",
        "a_attr": {
          "href": null
        }
      },
      {
        "text": "DOZISF__Get_Intel_Records_For_Upsert_Path",
        "icon": "fa-solid fa-circle-check icon-success",
        "a_attr": {
          "href": null
        }
      },
      {
        "text": "DOZISF__Get_Next_Run_Path",
        "icon": "fa-solid fa-circle-check icon-success",
        "a_attr": {
          "href": null
        }
      },
      {
        "text": "DOZISF__Get_Next_Run_Path",
        "icon": "fa-solid fa-circle-check icon-success",
        "a_attr": {
          "href": null
        }
      },
      {
        "text": "DOZISF__Get_Queries_For_Upsert_Path",
        "icon": "fa-solid fa-circle-check icon-success",
        "a_attr": {
          "href": null
        }
      },
      {
        "text": "DOZISF__Get_Queries_For_Upsert_Path",
        "icon": "fa-solid fa-circle-check icon-success",
        "a_attr": {
          "href": null
        }
      },
      {
        "text": "DOZISF__Get_Records_For_Sa_Flow_Path",
        "icon": "fa-solid fa-circle-check icon-success",
        "a_attr": {
          "href": null
        }
      },
      {
        "text": "DOZISF__Get_Records_For_Sa_Flow_Path",
        "icon": "fa-solid fa-circle-check icon-success",
        "a_attr": {
          "href": null
        }
      },
      {
        "text": "DOZISF__Get_Records_For_Upsert_Path",
        "icon": "fa-solid fa-circle-check icon-success",
        "a_attr": {
          "href": null
        }
      },
      {
        "text": "DOZISF__Get_Records_For_Upsert_Path",
        "icon": "fa-solid fa-circle-check icon-success",
        "a_attr": {
          "href": null
        }
      },
      {
        "text": "DOZISF__Get_Relation_Records_For_Insert_Path",
        "icon": "fa-solid fa-circle-check icon-success",
        "a_attr": {
          "href": null
        }
      },
      {
        "text": "DOZISF__Get_Relation_Records_For_Insert_Path",
        "icon": "fa-solid fa-circle-check icon-success",
        "a_attr": {
          "href": null
        }
      },
      {
        "text": "DOZISF__Log_Failed_Pages",
        "icon": "fa-solid fa-circle-check icon-success",
        "a_attr": {
          "href": null
        }
      },
      {
        "text": "DOZISF__Log_Failed_Pages",
        "icon": "fa-solid fa-circle-check icon-success",
        "a_attr": {
          "href": null
        }
      },
      {
        "text": "DOZISF__Parse_Find_Duplicate_Results_Path",
        "icon": "fa-solid fa-circle-check icon-success",
        "a_attr": {
          "href": null
        }
      },
      {
        "text": "DOZISF__Parse_Find_Duplicate_Results_Path",
        "icon": "fa-solid fa-circle-check icon-success",
        "a_attr": {
          "href": null
        }
      },
      {
        "text": "DOZISF__Parse_Find_Relation_Results_Path",
        "icon": "fa-solid fa-circle-check icon-success",
        "a_attr": {
          "href": null
        }
      },
      {
        "text": "DOZISF__Parse_Find_Relation_Results_Path",
        "icon": "fa-solid fa-circle-check icon-success",
        "a_attr": {
          "href": null
        }
      },
      {
        "text": "DOZISF__Parse_Intel_Export_Upsert_Results_Path",
        "icon": "fa-solid fa-circle-check icon-success",
        "a_attr": {
          "href": null
        }
      },
      {
        "text": "DOZISF__Parse_Intel_Export_Upsert_Results_Path",
        "icon": "fa-solid fa-circle-check icon-success",
        "a_attr": {
          "href": null
        }
      },
      {
        "text": "DOZISF__Parse_Upsert_Results_Path",
        "icon": "fa-solid fa-circle-check icon-success",
        "a_attr": {
          "href": null
        }
      },
      {
        "text": "DOZISF__Parse_Upsert_Results_Path",
        "icon": "fa-solid fa-circle-check icon-success",
        "a_attr": {
          "href": null
        }
      },
      {
        "text": "DOZISF__PR_Base_URL",
        "icon": "fa-solid fa-circle-check icon-success",
        "a_attr": {
          "href": null
        }
      },
      {
        "text": "DOZISF__PR_Base_URL",
        "icon": "fa-solid fa-circle-check icon-success",
        "a_attr": {
          "href": null
        }
      },
      {
        "text": "DOZISF__PR_UI_Base_URL",
        "icon": "fa-solid fa-circle-check icon-success",
        "a_attr": {
          "href": null
        }
      },
      {
        "text": "DOZISF__PR_UI_Base_URL",
        "icon": "fa-solid fa-circle-check icon-success",
        "a_attr": {
          "href": null
        }
      },
      {
        "text": "DOZISF__Pre_Production_UI_Base_URL",
        "icon": "fa-solid fa-circle-check icon-success",
        "a_attr": {
          "href": null
        }
      },
      {
        "text": "DOZISF__Pre_Production_UI_Base_URL",
        "icon": "fa-solid fa-circle-check icon-success",
        "a_attr": {
          "href": null
        }
      },
      {
        "text": "DOZISF__Production_Base_URL",
        "icon": "fa-solid fa-circle-check icon-success",
        "a_attr": {
          "href": null
        }
      },
      {
        "text": "DOZISF__Production_Base_URL",
        "icon": "fa-solid fa-circle-check icon-success",
        "a_attr": {
          "href": null
        }
      },
      {
        "text": "DOZISF__Production_Bulk_Export_Base_URL",
        "icon": "fa-solid fa-circle-check icon-success",
        "a_attr": {
          "href": null
        }
      },
      {
        "text": "DOZISF__Production_Bulk_Export_Base_URL",
        "icon": "fa-solid fa-circle-check icon-success",
        "a_attr": {
          "href": null
        }
      },
      {
        "text": "DOZISF__Production_Enrich_Base_URL",
        "icon": "fa-solid fa-circle-check icon-success",
        "a_attr": {
          "href": null
        }
      },
      {
        "text": "DOZISF__Production_Enrich_Base_URL",
        "icon": "fa-solid fa-circle-check icon-success",
        "a_attr": {
          "href": null
        }
      },
      {
        "text": "DOZISF__Production_UI_Base_URL",
        "icon": "fa-solid fa-circle-check icon-success",
        "a_attr": {
          "href": null
        }
      },
      {
        "text": "DOZISF__Production_UI_Base_URL",
        "icon": "fa-solid fa-circle-check icon-success",
        "a_attr": {
          "href": null
        }
      },
      {
        "text": "DOZISF__Regression_UI_Base_URL",
        "icon": "fa-solid fa-circle-check icon-success",
        "a_attr": {
          "href": null
        }
      },
      {
        "text": "DOZISF__Regression_UI_Base_URL",
        "icon": "fa-solid fa-circle-check icon-success",
        "a_attr": {
          "href": null
        }
      },
      {
        "text": "DOZISF__Run_After_Select_Duplicates_Path",
        "icon": "fa-solid fa-circle-check icon-success",
        "a_attr": {
          "href": null
        }
      },
      {
        "text": "DOZISF__Run_After_Select_Duplicates_Path",
        "icon": "fa-solid fa-circle-check icon-success",
        "a_attr": {
          "href": null
        }
      },
      {
        "text": "DOZISF__Run_After_Select_Relation_Path",
        "icon": "fa-solid fa-circle-check icon-success",
        "a_attr": {
          "href": null
        }
      },
      {
        "text": "DOZISF__Run_After_Select_Relation_Path",
        "icon": "fa-solid fa-circle-check icon-success",
        "a_attr": {
          "href": null
        }
      },
      {
        "text": "DOZISF__Send_Insert_Relation_Results_Path",
        "icon": "fa-solid fa-circle-check icon-success",
        "a_attr": {
          "href": null
        }
      },
      {
        "text": "DOZISF__Send_Insert_Relation_Results_Path",
        "icon": "fa-solid fa-circle-check icon-success",
        "a_attr": {
          "href": null
        }
      },
      {
        "text": "DOZISF__Send_Insert_Sa_Flow_Results",
        "icon": "fa-solid fa-circle-check icon-success",
        "a_attr": {
          "href": null
        }
      },
      {
        "text": "DOZISF__Send_Insert_Sa_Flow_Results",
        "icon": "fa-solid fa-circle-check icon-success",
        "a_attr": {
          "href": null
        }
      },
      {
        "text": "DOZISF__Staging_Base_URL",
        "icon": "fa-solid fa-circle-check icon-success",
        "a_attr": {
          "href": null
        }
      },
      {
        "text": "DOZISF__Staging_Base_URL",
        "icon": "fa-solid fa-circle-check icon-success",
        "a_attr": {
          "href": null
        }
      },
      {
        "text": "DOZISF__Staging_Bulk_Export_Base_URL",
        "icon": "fa-solid fa-circle-check icon-success",
        "a_attr": {
          "href": null
        }
      },
      {
        "text": "DOZISF__Staging_Bulk_Export_Base_URL",
        "icon": "fa-solid fa-circle-check icon-success",
        "a_attr": {
          "href": null
        }
      },
      {
        "text": "DOZISF__Staging_Enrich_Base_URL",
        "icon": "fa-solid fa-circle-check icon-success",
        "a_attr": {
          "href": null
        }
      },
      {
        "text": "DOZISF__Staging_Enrich_Base_URL",
        "icon": "fa-solid fa-circle-check icon-success",
        "a_attr": {
          "href": null
        }
      },
      {
        "text": "DOZISF__Staging_UI_Base_URL",
        "icon": "fa-solid fa-circle-check icon-success",
        "a_attr": {
          "href": null
        }
      },
      {
        "text": "DOZISF__Staging_UI_Base_URL",
        "icon": "fa-solid fa-circle-check icon-success",
        "a_attr": {
          "href": null
        }
      },
      {
        "text": "DOZISF__Start_Next_Run_Path",
        "icon": "fa-solid fa-circle-check icon-success",
        "a_attr": {
          "href": null
        }
      },
      {
        "text": "DOZISF__Start_Next_Run_Path",
        "icon": "fa-solid fa-circle-check icon-success",
        "a_attr": {
          "href": null
        }
      },
      {
        "text": "DOZISF__Update_Bulk_Export_Run_Status_Path",
        "icon": "fa-solid fa-circle-check icon-success",
        "a_attr": {
          "href": null
        }
      },
      {
        "text": "DOZISF__Update_Bulk_Export_Run_Status_Path",
        "icon": "fa-solid fa-circle-check icon-success",
        "a_attr": {
          "href": null
        }
      },
      {
        "text": "DOZISF__Update_Intel_Export_Run_Status_Path",
        "icon": "fa-solid fa-circle-check icon-success",
        "a_attr": {
          "href": null
        }
      },
      {
        "text": "DOZISF__Update_Intel_Export_Run_Status_Path",
        "icon": "fa-solid fa-circle-check icon-success",
        "a_attr": {
          "href": null
        }
      }
    ]
  },
  {
    "text": " Custom Metadata (1)",
    "icon": "fa-solid fa-folder icon-blue",
    "a_attr": {
      "href": null
    },
    "children": [
      {
        "text": "DOZISF__JWT_Setting.DOZISF__zi_auth",
        "icon": "fa-solid fa-circle-check icon-success",
        "a_attr": {
          "href": null
        }
      }
    ]
  },
  {
    "text": " Custom Object (5)",
    "icon": "fa-solid fa-folder icon-blue",
    "a_attr": {
      "href": null
    },
    "children": [
      {
        "text": "DOZISF__Complete_Setting__c",
        "icon": "fa-solid fa-circle-check icon-success",
        "a_attr": {
          "href": null
        }
      },
      {
        "text": "DOZISF__JWT_Setting__mdt",
        "icon": "fa-solid fa-circle-check icon-success",
        "a_attr": {
          "href": null
        }
      },
      {
        "text": "DOZISF__ZoomInfo__c",
        "icon": "fa-solid fa-circle-check icon-success",
        "a_attr": {
          "href": null
        }
      },
      {
        "text": "DOZISF__ZoomInfo_Intent__c",
        "icon": "fa-solid fa-circle-check icon-success",
        "a_attr": {
          "href": null
        }
      },
      {
        "text": "DOZISF__ZoomInfo_Scoop__c",
        "icon": "fa-solid fa-circle-check icon-success",
        "a_attr": {
          "href": null
        }
      }
    ]
  },
  {
    "text": " Custom Object Translation (5)",
    "icon": "fa-solid fa-folder icon-blue",
    "a_attr": {
      "href": null
    },
    "children": [
      {
        "text": "DOZISF__Complete_Setting__c-DOZISF__en_US",
        "icon": "fa-solid fa-circle-check icon-success",
        "a_attr": {
          "href": null
        }
      },
      {
        "text": "DOZISF__JWT_Setting__mdt-DOZISF__en_US",
        "icon": "fa-solid fa-circle-check icon-success",
        "a_attr": {
          "href": null
        }
      },
      {
        "text": "DOZISF__ZoomInfo__c-DOZISF__en_US",
        "icon": "fa-solid fa-circle-check icon-success",
        "a_attr": {
          "href": null
        }
      },
      {
        "text": "DOZISF__ZoomInfo_Intent__c-DOZISF__en_US",
        "icon": "fa-solid fa-circle-check icon-success",
        "a_attr": {
          "href": null
        }
      },
      {
        "text": "DOZISF__ZoomInfo_Scoop__c-DOZISF__en_US",
        "icon": "fa-solid fa-circle-check icon-success",
        "a_attr": {
          "href": null
        }
      }
    ]
  },
  {
    "text": " Custom Permission (1)",
    "icon": "fa-solid fa-folder icon-blue",
    "a_attr": {
      "href": null
    },
    "children": [
      {
        "text": "DOZISF__ZoomInfo",
        "icon": "fa-solid fa-circle-check icon-success",
        "a_attr": {
          "href": null
        }
      }
    ]
  },
  {
    "text": " Custom Tab (4)",
    "icon": "fa-solid fa-folder icon-blue",
    "a_attr": {
      "href": null
    },
    "children": [
      {
        "text": "DOZISF__ZoomInfo",
        "icon": "fa-solid fa-circle-check icon-success",
        "a_attr": {
          "href": null
        }
      },
      {
        "text": "DOZISF__ZoomInfo_Intent__c",
        "icon": "fa-solid fa-circle-check icon-success",
        "a_attr": {
          "href": null
        }
      },
      {
        "text": "DOZISF__ZoomInfo_LWC",
        "icon": "fa-solid fa-circle-check icon-success",
        "a_attr": {
          "href": null
        }
      },
      {
        "text": "DOZISF__ZoomInfo_Scoop__c",
        "icon": "fa-solid fa-circle-check icon-success",
        "a_attr": {
          "href": null
        }
      }
    ]
  },
  {
    "text": " Dashboard (2)",
    "icon": "fa-solid fa-folder icon-blue",
    "a_attr": {
      "href": null
    },
    "children": [
      {
        "text": "DOZISF__ZoomInfoDashboards/",
        "icon": "fa-solid fa-circle-check icon-success",
        "a_attr": {
          "href": null
        }
      },
      {
        "text": "DOZISF__ZoomInfoDashboards/DOZISF__enrfTWjLvOlBSogDELUPTDmeDJgCHF",
        "icon": "fa-solid fa-circle-check icon-success",
        "a_attr": {
          "href": null
        }
      }
    ]
  },
  {
    "text": " Document (2)",
    "icon": "fa-solid fa-folder icon-blue",
    "a_attr": {
      "href": null
    },
    "children": [
      {
        "text": "DOZISF__ZoomInfo",
        "icon": "fa-solid fa-circle-check icon-success",
        "a_attr": {
          "href": null
        }
      },
      {
        "text": "DOZISF__ZoomInfo/DOZISF__Logo.png",
        "icon": "fa-solid fa-circle-check icon-success",
        "a_attr": {
          "href": null
        }
      }
    ]
  },
  {
    "text": " Installed Package (1)",
    "icon": "fa-solid fa-folder icon-blue",
    "a_attr": {
      "href": null
    },
    "children": [
      {
        "text": "DOZISF",
        "icon": "fa-solid fa-circle-check icon-success",
        "a_attr": {
          "href": null
        }
      }
    ]
  },
  {
    "text": " Layout (6)",
    "icon": "fa-solid fa-folder icon-blue",
    "a_attr": {
      "href": null
    },
    "children": [
      {
        "text": "DOZISF__JWT_Setting__mdt-JWT Setting Layout",
        "icon": "fa-solid fa-circle-check icon-success",
        "a_attr": {
          "href": null
        }
      },
      {
        "text": "DOZISF__ZoomInfo__c-ZoomInfo Company",
        "icon": "fa-solid fa-circle-check icon-success",
        "a_attr": {
          "href": null
        }
      },
      {
        "text": "DOZISF__ZoomInfo__c-ZoomInfo Contact",
        "icon": "fa-solid fa-circle-check icon-success",
        "a_attr": {
          "href": null
        }
      },
      {
        "text": "DOZISF__ZoomInfo__c-ZoomInfo Layout",
        "icon": "fa-solid fa-circle-check icon-success",
        "a_attr": {
          "href": null
        }
      },
      {
        "text": "DOZISF__ZoomInfo_Intent__c-ZoomInfo Intent Layout",
        "icon": "fa-solid fa-circle-check icon-success",
        "a_attr": {
          "href": null
        }
      },
      {
        "text": "DOZISF__ZoomInfo_Scoop__c-ZoomInfo Scoop Layout",
        "icon": "fa-solid fa-circle-check icon-success",
        "a_attr": {
          "href": null
        }
      }
    ]
  },
  {
    "text": " Lightning Component Bundle (1)",
    "icon": "fa-solid fa-folder icon-blue",
    "a_attr": {
      "href": null
    },
    "children": [
      {
        "text": "DOZISF__zoominfoIframe",
        "icon": "fa-solid fa-circle-check icon-success",
        "a_attr": {
          "href": null
        }
      }
    ]
  },
  {
    "text": " List View (4)",
    "icon": "fa-solid fa-folder icon-blue",
    "a_attr": {
      "href": null
    },
    "children": [
      {
        "text": "DOZISF__ZoomInfo_Intent__c.DOZISF__All",
        "icon": "fa-solid fa-circle-check icon-success",
        "a_attr": {
          "href": null
        }
      },
      {
        "text": "DOZISF__ZoomInfo_Intent__c.DOZISF__All",
        "icon": "fa-solid fa-circle-check icon-success",
        "a_attr": {
          "href": null
        }
      },
      {
        "text": "DOZISF__ZoomInfo_Scoop__c.DOZISF__All",
        "icon": "fa-solid fa-circle-check icon-success",
        "a_attr": {
          "href": null
        }
      },
      {
        "text": "DOZISF__ZoomInfo_Scoop__c.DOZISF__All",
        "icon": "fa-solid fa-circle-check icon-success",
        "a_attr": {
          "href": null
        }
      }
    ]
  },
  {
    "text": " Permission Set (2)",
    "icon": "fa-solid fa-folder icon-blue",
    "a_attr": {
      "href": null
    },
    "children": [
      {
        "text": "DOZISF__ZoomInfo_Admin",
        "icon": "fa-solid fa-circle-check icon-success",
        "a_attr": {
          "href": null
        }
      },
      {
        "text": "DOZISF__ZoomInfo_User",
        "icon": "fa-solid fa-circle-check icon-success",
        "a_attr": {
          "href": null
        }
      }
    ]
  },
  {
    "text": " Record Type (3)",
    "icon": "fa-solid fa-folder icon-blue",
    "a_attr": {
      "href": null
    },
    "children": [
      {
        "text": "DOZISF__ZoomInfo__c.DOZISF__Company",
        "icon": "fa-solid fa-circle-check icon-success",
        "a_attr": {
          "href": null
        }
      },
      {
        "text": "DOZISF__ZoomInfo__c.DOZISF__Contact",
        "icon": "fa-solid fa-circle-check icon-success",
        "a_attr": {
          "href": null
        }
      },
      {
        "text": "DOZISF__ZoomInfo__c.DOZISF__ZoomInfo",
        "icon": "fa-solid fa-circle-check icon-success",
        "a_attr": {
          "href": null
        }
      }
    ]
  },
  {
    "text": " Remote Site Setting (2)",
    "icon": "fa-solid fa-folder icon-blue",
    "a_attr": {
      "href": null
    },
    "children": [
      {
        "text": "DOZISF__BulkExport",
        "icon": "fa-solid fa-circle-check icon-success",
        "a_attr": {
          "href": null
        }
      },
      {
        "text": "DOZISF__Enrich",
        "icon": "fa-solid fa-circle-check icon-success",
        "a_attr": {
          "href": null
        }
      }
    ]
  },
  {
    "text": " Report (11)",
    "icon": "fa-solid fa-folder icon-blue",
    "a_attr": {
      "href": null
    },
    "children": [
      {
        "text": "DOZISF__ZoomInfo_Reports/",
        "icon": "fa-solid fa-circle-check icon-success",
        "a_attr": {
          "href": null
        }
      },
      {
        "text": "DOZISF__ZoomInfo_Reports/DOZISF__Activities_pVf",
        "icon": "fa-solid fa-circle-check icon-success",
        "a_attr": {
          "href": null
        }
      },
      {
        "text": "DOZISF__ZoomInfo_Reports/DOZISF__Activities_with_ZoomInfo_Lead_RQc",
        "icon": "fa-solid fa-circle-check icon-success",
        "a_attr": {
          "href": null
        }
      },
      {
        "text": "DOZISF__ZoomInfo_Reports/DOZISF__Closed_Won_Amount_with_ZoomInfo_Account_mK5",
        "icon": "fa-solid fa-circle-check icon-success",
        "a_attr": {
          "href": null
        }
      },
      {
        "text": "DOZISF__ZoomInfo_Reports/DOZISF__Contacts_F25",
        "icon": "fa-solid fa-circle-check icon-success",
        "a_attr": {
          "href": null
        }
      },
      {
        "text": "DOZISF__ZoomInfo_Reports/DOZISF__Open_Opportunities_with_ZoomInfo_Account_a9O",
        "icon": "fa-solid fa-circle-check icon-success",
        "a_attr": {
          "href": null
        }
      },
      {
        "text": "DOZISF__ZoomInfo_Reports/DOZISF__Opportunities_with_ZoomInfo_Account_ZjD",
        "icon": "fa-solid fa-circle-check icon-success",
        "a_attr": {
          "href": null
        }
      },
      {
        "text": "DOZISF__ZoomInfo_Reports/DOZISF__Opportunities_with_ZoomInfo_Contact_qFb",
        "icon": "fa-solid fa-circle-check icon-success",
        "a_attr": {
          "href": null
        }
      },
      {
        "text": "DOZISF__ZoomInfo_Reports/DOZISF__Opportunity_w_Contacts_Win_Rate_jbu",
        "icon": "fa-solid fa-circle-check icon-success",
        "a_attr": {
          "href": null
        }
      },
      {
        "text": "DOZISF__ZoomInfo_Reports/DOZISF__ZoomInfo_Accounts_pKj",
        "icon": "fa-solid fa-circle-check icon-success",
        "a_attr": {
          "href": null
        }
      },
      {
        "text": "DOZISF__ZoomInfo_Reports/DOZISF__ZoomInfo_Leads_Qne",
        "icon": "fa-solid fa-circle-check icon-success",
        "a_attr": {
          "href": null
        }
      }
    ]
  },
  {
    "text": " Sharing Rules (3)",
    "icon": "fa-solid fa-folder icon-blue",
    "a_attr": {
      "href": null
    },
    "children": [
      {
        "text": "DOZISF__ZoomInfo__c",
        "icon": "fa-solid fa-circle-check icon-success",
        "a_attr": {
          "href": null
        }
      },
      {
        "text": "DOZISF__ZoomInfo_Intent__c",
        "icon": "fa-solid fa-circle-check icon-success",
        "a_attr": {
          "href": null
        }
      },
      {
        "text": "DOZISF__ZoomInfo_Scoop__c",
        "icon": "fa-solid fa-circle-check icon-success",
        "a_attr": {
          "href": null
        }
      }
    ]
  },
  {
    "text": " Static Resource (23)",
    "icon": "fa-solid fa-folder icon-blue",
    "a_attr": {
      "href": null
    },
    "children": [
      {
        "text": "DOZISF__confirmation",
        "icon": "fa-solid fa-circle-check icon-success",
        "a_attr": {
          "href": null
        }
      },
      {
        "text": "DOZISF__getFindDuplicateQueries",
        "icon": "fa-solid fa-circle-check icon-success",
        "a_attr": {
          "href": null
        }
      },
      {
        "text": "DOZISF__getFindRelationQueries",
        "icon": "fa-solid fa-circle-check icon-success",
        "a_attr": {
          "href": null
        }
      },
      {
        "text": "DOZISF__getIntelExportRecordsForUpsert",
        "icon": "fa-solid fa-circle-check icon-success",
        "a_attr": {
          "href": null
        }
      },
      {
        "text": "DOZISF__getIntelExportRun",
        "icon": "fa-solid fa-circle-check icon-success",
        "a_attr": {
          "href": null
        }
      },
      {
        "text": "DOZISF__getIntelExportRunNotNeeded",
        "icon": "fa-solid fa-circle-check icon-success",
        "a_attr": {
          "href": null
        }
      },
      {
        "text": "DOZISF__getMultiTypeRecordsForUpsert",
        "icon": "fa-solid fa-circle-check icon-success",
        "a_attr": {
          "href": null
        }
      },
      {
        "text": "DOZISF__getQueriesForUpsert",
        "icon": "fa-solid fa-circle-check icon-success",
        "a_attr": {
          "href": null
        }
      },
      {
        "text": "DOZISF__getRecordsForSaFlow",
        "icon": "fa-solid fa-circle-check icon-success",
        "a_attr": {
          "href": null
        }
      },
      {
        "text": "DOZISF__getRecordsForUpsert",
        "icon": "fa-solid fa-circle-check icon-success",
        "a_attr": {
          "href": null
        }
      },
      {
        "text": "DOZISF__getRelationRecordsForInsert",
        "icon": "fa-solid fa-circle-check icon-success",
        "a_attr": {
          "href": null
        }
      },
      {
        "text": "DOZISF__RestUtilityTestResponse",
        "icon": "fa-solid fa-circle-check icon-success",
        "a_attr": {
          "href": null
        }
      },
      {
        "text": "DOZISF__runAfterSelectDuplicatesCreateRelation",
        "icon": "fa-solid fa-circle-check icon-success",
        "a_attr": {
          "href": null
        }
      },
      {
        "text": "DOZISF__runAfterSelectDuplicatesUpsertProgress",
        "icon": "fa-solid fa-circle-check icon-success",
        "a_attr": {
          "href": null
        }
      },
      {
        "text": "DOZISF__runAfterSelectRelation",
        "icon": "fa-solid fa-circle-check icon-success",
        "a_attr": {
          "href": null
        }
      },
      {
        "text": "DOZISF__runStatusDone",
        "icon": "fa-solid fa-circle-check icon-success",
        "a_attr": {
          "href": null
        }
      },
      {
        "text": "DOZISF__runStatusProgressFindDuplicates",
        "icon": "fa-solid fa-circle-check icon-success",
        "a_attr": {
          "href": null
        }
      },
      {
        "text": "DOZISF__runStatusProgressFindRelation",
        "icon": "fa-solid fa-circle-check icon-success",
        "a_attr": {
          "href": null
        }
      },
      {
        "text": "DOZISF__runStatusQueued",
        "icon": "fa-solid fa-circle-check icon-success",
        "a_attr": {
          "href": null
        }
      },
      {
        "text": "DOZISF__updateRunStatusCreateRelation",
        "icon": "fa-solid fa-circle-check icon-success",
        "a_attr": {
          "href": null
        }
      },
      {
        "text": "DOZISF__updateRunStatusDone",
        "icon": "fa-solid fa-circle-check icon-success",
        "a_attr": {
          "href": null
        }
      },
      {
        "text": "DOZISF__updateRunStatusFindDuplicate",
        "icon": "fa-solid fa-circle-check icon-success",
        "a_attr": {
          "href": null
        }
      },
      {
        "text": "DOZISF__updateRunStatusUpsertProgress",
        "icon": "fa-solid fa-circle-check icon-success",
        "a_attr": {
          "href": null
        }
      }
    ]
  },
  {
    "text": " Topics For Objects (3)",
    "icon": "fa-solid fa-folder icon-blue",
    "a_attr": {
      "href": null
    },
    "children": [
      {
        "text": "DOZISF__ZoomInfo__c",
        "icon": "fa-solid fa-circle-check icon-success",
        "a_attr": {
          "href": null
        }
      },
      {
        "text": "DOZISF__ZoomInfo_Intent__c",
        "icon": "fa-solid fa-circle-check icon-success",
        "a_attr": {
          "href": null
        }
      },
      {
        "text": "DOZISF__ZoomInfo_Scoop__c",
        "icon": "fa-solid fa-circle-check icon-success",
        "a_attr": {
          "href": null
        }
      }
    ]
  },
  {
    "text": " Workflow (1)",
    "icon": "fa-solid fa-folder icon-blue",
    "a_attr": {
      "href": null
    },
    "children": [
      {
        "text": "DOZISF__ZoomInfo__c",
        "icon": "fa-solid fa-circle-check icon-success",
        "a_attr": {
          "href": null
        }
      }
    ]
  },
  {
    "text": " Workflow Field Update (2)",
    "icon": "fa-solid fa-folder icon-blue",
    "a_attr": {
      "href": null
    },
    "children": [
      {
        "text": "DOZISF__ZoomInfo__c.DOZISF__ZoomInfo_Set_Company_Record_Type",
        "icon": "fa-solid fa-circle-check icon-success",
        "a_attr": {
          "href": null
        }
      },
      {
        "text": "DOZISF__ZoomInfo__c.DOZISF__ZoomInfo_Set_Contact_Record_Type",
        "icon": "fa-solid fa-circle-check icon-success",
        "a_attr": {
          "href": null
        }
      }
    ]
  },
  {
    "text": " Workflow Rule (2)",
    "icon": "fa-solid fa-folder icon-blue",
    "a_attr": {
      "href": null
    },
    "children": [
      {
        "text": "DOZISF__ZoomInfo__c.DOZISF__ZoomInfo Company Created",
        "icon": "fa-solid fa-circle-check icon-success",
        "a_attr": {
          "href": null
        }
      },
      {
        "text": "DOZISF__ZoomInfo__c.DOZISF__ZoomInfo Contact Created",
        "icon": "fa-solid fa-circle-check icon-success",
        "a_attr": {
          "href": null
        }
      }
    ]
  }
]