[
  {
    "text": " Apex Class (35)",
    "icon": "fa-solid fa-folder icon-blue",
    "a_attr": {
      "href": null
    },
    "children": [
      {
        "text": "Profile2PermSet__constants",
        "icon": "fa-solid fa-circle-check icon-success",
        "a_attr": {
          "href": null
        }
      },
      {
        "text": "Profile2PermSet__dmlManager",
        "icon": "fa-solid fa-circle-check icon-success",
        "a_attr": {
          "href": null
        }
      },
      {
        "text": "Profile2PermSet__FieldPermissionsBatchCloner",
        "icon": "fa-solid fa-circle-check icon-success",
        "a_attr": {
          "href": null
        }
      },
      {
        "text": "Profile2PermSet__ObjectPermissionsBatchCloner",
        "icon": "fa-solid fa-circle-check icon-success",
        "a_attr": {
          "href": null
        }
      },
      {
        "text": "Profile2PermSet__permAnalyzer",
        "icon": "fa-solid fa-circle-check icon-success",
        "a_attr": {
          "href": null
        }
      },
      {
        "text": "Profile2PermSet__permAnalyzerTestData",
        "icon": "fa-solid fa-circle-check icon-success",
        "a_attr": {
          "href": null
        }
      },
      {
        "text": "Profile2PermSet__permissionManager",
        "icon": "fa-solid fa-circle-check icon-success",
        "a_attr": {
          "href": null
        }
      },
      {
        "text": "Profile2PermSet__PermissionsBatchCloner",
        "icon": "fa-solid fa-circle-check icon-success",
        "a_attr": {
          "href": null
        }
      },
      {
        "text": "Profile2PermSet__PermissionsBatchCloner_Test",
        "icon": "fa-solid fa-circle-check icon-success",
        "a_attr": {
          "href": null
        }
      },
      {
        "text": "Profile2PermSet__permissionSetGroupsList",
        "icon": "fa-solid fa-circle-check icon-success",
        "a_attr": {
          "href": null
        }
      },
      {
        "text": "Profile2PermSet__PermissionsHelper",
        "icon": "fa-solid fa-circle-check icon-success",
        "a_attr": {
          "href": null
        }
      },
      {
        "text": "Profile2PermSet__PermissionsHelper_Test",
        "icon": "fa-solid fa-circle-check icon-success",
        "a_attr": {
          "href": null
        }
      },
      {
        "text": "Profile2PermSet__profileConverter",
        "icon": "fa-solid fa-circle-check icon-success",
        "a_attr": {
          "href": null
        }
      },
      {
        "text": "Profile2PermSet__psgAgregatedPermissions",
        "icon": "fa-solid fa-circle-check icon-success",
        "a_attr": {
          "href": null
        }
      },
      {
        "text": "Profile2PermSet__report",
        "icon": "fa-solid fa-circle-check icon-success",
        "a_attr": {
          "href": null
        }
      },
      {
        "text": "Profile2PermSet__reportByPermissionDependency",
        "icon": "fa-solid fa-circle-check icon-success",
        "a_attr": {
          "href": null
        }
      },
      {
        "text": "Profile2PermSet__reportByPermissionSet",
        "icon": "fa-solid fa-circle-check icon-success",
        "a_attr": {
          "href": null
        }
      },
      {
        "text": "Profile2PermSet__reportByUser",
        "icon": "fa-solid fa-circle-check icon-success",
        "a_attr": {
          "href": null
        }
      },
      {
        "text": "Profile2PermSet__responseData",
        "icon": "fa-solid fa-circle-check icon-success",
        "a_attr": {
          "href": null
        }
      },
      {
        "text": "Profile2PermSet__SetupEntityAccessBatchCloner",
        "icon": "fa-solid fa-circle-check icon-success",
        "a_attr": {
          "href": null
        }
      },
      {
        "text": "Profile2PermSet__strike_lookupController",
        "icon": "fa-solid fa-circle-check icon-success",
        "a_attr": {
          "href": null
        }
      },
      {
        "text": "Profile2PermSet__strike_tst_lookupController",
        "icon": "fa-solid fa-circle-check icon-success",
        "a_attr": {
          "href": null
        }
      },
      {
        "text": "Profile2PermSet__strike_utilities",
        "icon": "fa-solid fa-circle-check icon-success",
        "a_attr": {
          "href": null
        }
      },
      {
        "text": "Profile2PermSet__TabSettingBatchCloner",
        "icon": "fa-solid fa-circle-check icon-success",
        "a_attr": {
          "href": null
        }
      },
      {
        "text": "Profile2PermSet__tst_permAnalyzer",
        "icon": "fa-solid fa-circle-check icon-success",
        "a_attr": {
          "href": null
        }
      },
      {
        "text": "Profile2PermSet__tst_permissionManager",
        "icon": "fa-solid fa-circle-check icon-success",
        "a_attr": {
          "href": null
        }
      },
      {
        "text": "Profile2PermSet__tst_permissionSetGroups",
        "icon": "fa-solid fa-circle-check icon-success",
        "a_attr": {
          "href": null
        }
      },
      {
        "text": "Profile2PermSet__tst_profileCoverter",
        "icon": "fa-solid fa-circle-check icon-success",
        "a_attr": {
          "href": null
        }
      },
      {
        "text": "Profile2PermSet__tst_report",
        "icon": "fa-solid fa-circle-check icon-success",
        "a_attr": {
          "href": null
        }
      },
      {
        "text": "Profile2PermSet__tst_reportByPermissionDependency",
        "icon": "fa-solid fa-circle-check icon-success",
        "a_attr": {
          "href": null
        }
      },
      {
        "text": "Profile2PermSet__tst_reportByPermissionSet",
        "icon": "fa-solid fa-circle-check icon-success",
        "a_attr": {
          "href": null
        }
      },
      {
        "text": "Profile2PermSet__tst_reportByUser",
        "icon": "fa-solid fa-circle-check icon-success",
        "a_attr": {
          "href": null
        }
      },
      {
        "text": "Profile2PermSet__tst_userMode",
        "icon": "fa-solid fa-circle-check icon-success",
        "a_attr": {
          "href": null
        }
      },
      {
        "text": "Profile2PermSet__userMode",
        "icon": "fa-solid fa-circle-check icon-success",
        "a_attr": {
          "href": null
        }
      },
      {
        "text": "Profile2PermSet__utilities",
        "icon": "fa-solid fa-circle-check icon-success",
        "a_attr": {
          "href": null
        }
      }
    ]
  },
  {
    "text": " Aura Definition Bundle (30)",
    "icon": "fa-solid fa-folder icon-blue",
    "a_attr": {
      "href": null
    },
    "children": [
      {
        "text": "Profile2PermSet__assignedPermsetList",
        "icon": "fa-solid fa-circle-check icon-success",
        "a_attr": {
          "href": null
        }
      },
      {
        "text": "Profile2PermSet__assignedUsersList",
        "icon": "fa-solid fa-circle-check icon-success",
        "a_attr": {
          "href": null
        }
      },
      {
        "text": "Profile2PermSet__attributeEvent",
        "icon": "fa-solid fa-circle-check icon-success",
        "a_attr": {
          "href": null
        }
      },
      {
        "text": "Profile2PermSet__defaultTokens",
        "icon": "fa-solid fa-circle-check icon-success",
        "a_attr": {
          "href": null
        }
      },
      {
        "text": "Profile2PermSet__multiSelect",
        "icon": "fa-solid fa-circle-check icon-success",
        "a_attr": {
          "href": null
        }
      },
      {
        "text": "Profile2PermSet__objectPermissions",
        "icon": "fa-solid fa-circle-check icon-success",
        "a_attr": {
          "href": null
        }
      },
      {
        "text": "Profile2PermSet__pa_cell",
        "icon": "fa-solid fa-circle-check icon-success",
        "a_attr": {
          "href": null
        }
      },
      {
        "text": "Profile2PermSet__pa_popover",
        "icon": "fa-solid fa-circle-check icon-success",
        "a_attr": {
          "href": null
        }
      },
      {
        "text": "Profile2PermSet__permAnalyzer",
        "icon": "fa-solid fa-circle-check icon-success",
        "a_attr": {
          "href": null
        }
      },
      {
        "text": "Profile2PermSet__permissionMode",
        "icon": "fa-solid fa-circle-check icon-success",
        "a_attr": {
          "href": null
        }
      },
      {
        "text": "Profile2PermSet__permissionSetGroups",
        "icon": "fa-solid fa-circle-check icon-success",
        "a_attr": {
          "href": null
        }
      },
      {
        "text": "Profile2PermSet__permissionSetGroupsDetailPage",
        "icon": "fa-solid fa-circle-check icon-success",
        "a_attr": {
          "href": null
        }
      },
      {
        "text": "Profile2PermSet__popover",
        "icon": "fa-solid fa-circle-check icon-success",
        "a_attr": {
          "href": null
        }
      },
      {
        "text": "Profile2PermSet__profileConverter",
        "icon": "fa-solid fa-circle-check icon-success",
        "a_attr": {
          "href": null
        }
      },
      {
        "text": "Profile2PermSet__psgHeader",
        "icon": "fa-solid fa-circle-check icon-success",
        "a_attr": {
          "href": null
        }
      },
      {
        "text": "Profile2PermSet__psgObjectPermissions",
        "icon": "fa-solid fa-circle-check icon-success",
        "a_attr": {
          "href": null
        }
      },
      {
        "text": "Profile2PermSet__psgUserPermissions",
        "icon": "fa-solid fa-circle-check icon-success",
        "a_attr": {
          "href": null
        }
      },
      {
        "text": "Profile2PermSet__report",
        "icon": "fa-solid fa-circle-check icon-success",
        "a_attr": {
          "href": null
        }
      },
      {
        "text": "Profile2PermSet__reportByPermissionDependency",
        "icon": "fa-solid fa-circle-check icon-success",
        "a_attr": {
          "href": null
        }
      },
      {
        "text": "Profile2PermSet__reportByPermissionSet",
        "icon": "fa-solid fa-circle-check icon-success",
        "a_attr": {
          "href": null
        }
      },
      {
        "text": "Profile2PermSet__reportByUser",
        "icon": "fa-solid fa-circle-check icon-success",
        "a_attr": {
          "href": null
        }
      },
      {
        "text": "Profile2PermSet__singleSelect",
        "icon": "fa-solid fa-circle-check icon-success",
        "a_attr": {
          "href": null
        }
      },
      {
        "text": "Profile2PermSet__strike_evt",
        "icon": "fa-solid fa-circle-check icon-success",
        "a_attr": {
          "href": null
        }
      },
      {
        "text": "Profile2PermSet__strike_lookup",
        "icon": "fa-solid fa-circle-check icon-success",
        "a_attr": {
          "href": null
        }
      },
      {
        "text": "Profile2PermSet__strike_modal",
        "icon": "fa-solid fa-circle-check icon-success",
        "a_attr": {
          "href": null
        }
      },
      {
        "text": "Profile2PermSet__strike_svg",
        "icon": "fa-solid fa-circle-check icon-success",
        "a_attr": {
          "href": null
        }
      },
      {
        "text": "Profile2PermSet__strike_tooltip",
        "icon": "fa-solid fa-circle-check icon-success",
        "a_attr": {
          "href": null
        }
      },
      {
        "text": "Profile2PermSet__toast",
        "icon": "fa-solid fa-circle-check icon-success",
        "a_attr": {
          "href": null
        }
      },
      {
        "text": "Profile2PermSet__userMode",
        "icon": "fa-solid fa-circle-check icon-success",
        "a_attr": {
          "href": null
        }
      },
      {
        "text": "Profile2PermSet__userPermissions",
        "icon": "fa-solid fa-circle-check icon-success",
        "a_attr": {
          "href": null
        }
      }
    ]
  },
  {
    "text": " Content Asset (3)",
    "icon": "fa-solid fa-folder icon-blue",
    "a_attr": {
      "href": null
    },
    "children": [
      {
        "text": "Profile2PermSet__icon",
        "icon": "fa-solid fa-circle-check icon-success",
        "a_attr": {
          "href": null
        }
      },
      {
        "text": "Profile2PermSet__PHicon",
        "icon": "fa-solid fa-circle-check icon-success",
        "a_attr": {
          "href": null
        }
      },
      {
        "text": "Profile2PermSet__salesforcenonamelogo",
        "icon": "fa-solid fa-circle-check icon-success",
        "a_attr": {
          "href": null
        }
      }
    ]
  },
  {
    "text": " Custom Application (1)",
    "icon": "fa-solid fa-folder icon-blue",
    "a_attr": {
      "href": null
    },
    "children": [
      {
        "text": "Profile2PermSet__Profiles_to_Permission_Sets",
        "icon": "fa-solid fa-circle-check icon-success",
        "a_attr": {
          "href": null
        }
      }
    ]
  },
  {
    "text": " Custom Label (10)",
    "icon": "fa-solid fa-folder icon-blue",
    "a_attr": {
      "href": null
    },
    "children": [
      {
        "text": "Profile2PermSet__dmlmanager_errorMessage_insufficientAccessField",
        "icon": "fa-solid fa-circle-check icon-success",
        "a_attr": {
          "href": null
        }
      },
      {
        "text": "Profile2PermSet__dmlmanager_errorMessage_insufficientAccessField",
        "icon": "fa-solid fa-circle-check icon-success",
        "a_attr": {
          "href": null
        }
      },
      {
        "text": "Profile2PermSet__dmlmanager_errorMessage_insufficientAccessObject",
        "icon": "fa-solid fa-circle-check icon-success",
        "a_attr": {
          "href": null
        }
      },
      {
        "text": "Profile2PermSet__dmlmanager_errorMessage_insufficientAccessObject",
        "icon": "fa-solid fa-circle-check icon-success",
        "a_attr": {
          "href": null
        }
      },
      {
        "text": "Profile2PermSet__dmlmanager_errormessage_unknownaccess",
        "icon": "fa-solid fa-circle-check icon-success",
        "a_attr": {
          "href": null
        }
      },
      {
        "text": "Profile2PermSet__dmlmanager_errormessage_unknownaccess",
        "icon": "fa-solid fa-circle-check icon-success",
        "a_attr": {
          "href": null
        }
      },
      {
        "text": "Profile2PermSet__dmlmanager_errorMessage_unknownField",
        "icon": "fa-solid fa-circle-check icon-success",
        "a_attr": {
          "href": null
        }
      },
      {
        "text": "Profile2PermSet__dmlmanager_errorMessage_unknownField",
        "icon": "fa-solid fa-circle-check icon-success",
        "a_attr": {
          "href": null
        }
      },
      {
        "text": "Profile2PermSet__dmlmanager_errorMessage_unknownObject",
        "icon": "fa-solid fa-circle-check icon-success",
        "a_attr": {
          "href": null
        }
      },
      {
        "text": "Profile2PermSet__dmlmanager_errorMessage_unknownObject",
        "icon": "fa-solid fa-circle-check icon-success",
        "a_attr": {
          "href": null
        }
      }
    ]
  },
  {
    "text": " Custom Tab (4)",
    "icon": "fa-solid fa-folder icon-blue",
    "a_attr": {
      "href": null
    },
    "children": [
      {
        "text": "Profile2PermSet__Converter",
        "icon": "fa-solid fa-circle-check icon-success",
        "a_attr": {
          "href": null
        }
      },
      {
        "text": "Profile2PermSet__Manage",
        "icon": "fa-solid fa-circle-check icon-success",
        "a_attr": {
          "href": null
        }
      },
      {
        "text": "Profile2PermSet__Permissions_Analyzer",
        "icon": "fa-solid fa-circle-check icon-success",
        "a_attr": {
          "href": null
        }
      },
      {
        "text": "Profile2PermSet__Report",
        "icon": "fa-solid fa-circle-check icon-success",
        "a_attr": {
          "href": null
        }
      }
    ]
  },
  {
    "text": " Installed Package (1)",
    "icon": "fa-solid fa-folder icon-blue",
    "a_attr": {
      "href": null
    },
    "children": [
      {
        "text": "Profile2PermSet",
        "icon": "fa-solid fa-circle-check icon-success",
        "a_attr": {
          "href": null
        }
      }
    ]
  },
  {
    "text": " Lightning Component Bundle (8)",
    "icon": "fa-solid fa-folder icon-blue",
    "a_attr": {
      "href": null
    },
    "children": [
      {
        "text": "Profile2PermSet__modal",
        "icon": "fa-solid fa-circle-check icon-success",
        "a_attr": {
          "href": null
        }
      },
      {
        "text": "Profile2PermSet__permissionManager",
        "icon": "fa-solid fa-circle-check icon-success",
        "a_attr": {
          "href": null
        }
      },
      {
        "text": "Profile2PermSet__permissionSetGroup",
        "icon": "fa-solid fa-circle-check icon-success",
        "a_attr": {
          "href": null
        }
      },
      {
        "text": "Profile2PermSet__permissionsTable",
        "icon": "fa-solid fa-circle-check icon-success",
        "a_attr": {
          "href": null
        }
      },
      {
        "text": "Profile2PermSet__permissionsTypeSection",
        "icon": "fa-solid fa-circle-check icon-success",
        "a_attr": {
          "href": null
        }
      },
      {
        "text": "Profile2PermSet__permSetGroupAssignments",
        "icon": "fa-solid fa-circle-check icon-success",
        "a_attr": {
          "href": null
        }
      },
      {
        "text": "Profile2PermSet__picklist",
        "icon": "fa-solid fa-circle-check icon-success",
        "a_attr": {
          "href": null
        }
      },
      {
        "text": "Profile2PermSet__picklistOption",
        "icon": "fa-solid fa-circle-check icon-success",
        "a_attr": {
          "href": null
        }
      }
    ]
  },
  {
    "text": " Permission Set (1)",
    "icon": "fa-solid fa-folder icon-blue",
    "a_attr": {
      "href": null
    },
    "children": [
      {
        "text": "Profile2PermSet__Profiles_to_Perm_Set_App_Access",
        "icon": "fa-solid fa-circle-check icon-success",
        "a_attr": {
          "href": null
        }
      }
    ]
  },
  {
    "text": " Static Resource (5)",
    "icon": "fa-solid fa-folder icon-blue",
    "a_attr": {
      "href": null
    },
    "children": [
      {
        "text": "Profile2PermSet__emptyState",
        "icon": "fa-solid fa-circle-check icon-success",
        "a_attr": {
          "href": null
        }
      },
      {
        "text": "Profile2PermSet__FileSaver",
        "icon": "fa-solid fa-circle-check icon-success",
        "a_attr": {
          "href": null
        }
      },
      {
        "text": "Profile2PermSet__JSZip",
        "icon": "fa-solid fa-circle-check icon-success",
        "a_attr": {
          "href": null
        }
      },
      {
        "text": "Profile2PermSet__PermDepExample",
        "icon": "fa-solid fa-circle-check icon-success",
        "a_attr": {
          "href": null
        }
      },
      {
        "text": "Profile2PermSet__samplePermDependencyReport",
        "icon": "fa-solid fa-circle-check icon-success",
        "a_attr": {
          "href": null
        }
      }
    ]
  }
]